simple_prompt_manager/__init__.py
simple_prompt_manager/simple_prompt_manager.py
simple_prompt_manager-0.1.3.dist-info/licenses/LICENSE
tests/__init__.py
tests/test_simple_prompt_manager.py
simple_prompt_manager-0.1.3.dist-info/METADATA
simple_prompt_manager-0.1.3.dist-info/WHEEL
simple_prompt_manager-0.1.3.dist-info/top_level.txt
simple_prompt_manager-0.1.3.dist-info/RECORD
