Metadata-Version: 2.4
Name: simple-prompt-manager
Version: 0.1.3
Summary: A very simple prompt management tool
Author-email: Erika Matesz <erikamatesz@protonmail.com>
License-Expression: MIT
Project-URL: Homepage, https://github.com/erikamatesz/simple-prompt-manager
Classifier: Development Status :: 3 - Alpha
Classifier: Intended Audience :: Developers
Classifier: Programming Language :: Python :: 3
Classifier: Programming Language :: Python :: 3.6
Classifier: Programming Language :: Python :: 3.7
Classifier: Programming Language :: Python :: 3.8
Classifier: Programming Language :: Python :: 3.9
Classifier: Programming Language :: Python :: 3.10
Classifier: Programming Language :: Python :: 3.11
Classifier: Programming Language :: Python :: 3.12
Requires-Python: >=3.6
License-File: LICENSE
Provides-Extra: dev
Requires-Dist: pytest>=6.0; extra == "dev"
Requires-Dist: pytest-cov; extra == "dev"
Dynamic: license-file
